stresstify.py
stresstify-0.1.2.dist-info/licenses/LICENSE.txt
stresstify-0.1.2.dist-info/METADATA
stresstify-0.1.2.dist-info/WHEEL
stresstify-0.1.2.dist-info/top_level.txt
stresstify-0.1.2.dist-info/RECORD
