Metadata-Version: 2.4
Name: stresstify
Version: 0.1.2
Summary: stresstify is a Python package designed for retrieving system information and performing stress tests on CPU, RAM, and disk. It provides detailed CPU information, including name, core count, frequency, and usage, as well as memory and disk usage statistics. The package includes stress tests such as CPU-intensive calculations across multiple cores, continuous RAM allocation until failure, and disk write speed measurement. The author is not responsible for any hardware damage caused by ex
Author: Pinkysha
License: MIT License
Classifier: Programming Language :: Python :: 3
Classifier: Operating System :: OS Independent
Requires-Python: >=3.10
License-File: LICENSE.txt
Requires-Dist: numpy==2.3.2
Requires-Dist: psutil==7.0.0
Requires-Dist: py-cpuinfo==9.0.0
Requires-Dist: plotext==5.3.2
Requires-Dist: matplotlib==3.10.6
Dynamic: license-file
